{
  "ticketId": "DF-233",
  "issueNumber": 147,
  "status": "blocked",
  "validationKind": "blocked",
  "generatedAt": "2026-06-21T23:41:04Z",
  "packageArchiveSha256": "0354291e6c6ac847335ba5095e088d1122a3bf93937589021edabb3e4fbcc913",
  "summary": "Queue throttling, retry, cancellation, resume, and product evidence writers are implemented. One real Codex Generate-runner smoke produced a succeeded one-slide queue artifact, and a product queue-control smoke now writes ready DF-233 evidence for a bounded 5xx retry and restart-resume run. No packaged Codex OAuth image run has captured genuine provider retry, user cancellation, and restart-resume evidence from the app surface.",
  "currentEvidence": [
    {
      "path": "docs/live-image-queue-controls.md",
      "kind": "image queue control contract"
    },
    {
      "path": "src/lib/live-image-queue-evidence-export.ts",
      "kind": "product queue evidence writer with stored image artifact path validation"
    },
    {
      "path": "src/lib/live-image-queue-evidence-export.test.ts",
      "kind": "stored image artifact path false-ready regression tests"
    },
    {
      "path": "src/lib/live-image-queue-restart-resume-evidence.ts",
      "kind": "restart-resume evidence validator with duplicate and overlap artifact id blocking"
    },
    {
      "path": "src/lib/live-image-queue-evidence-export-resume.test.ts",
      "kind": "restart-resume artifact overlap regression tests"
    },
    {
      "path": "src/lib/local-data-control.ts",
      "kind": "project folder export includes project-scoped browser artifact writes"
    },
    {
      "path": "src/lib/local-data-control.test.ts",
      "kind": "project artifact write export, filtering, and redaction regression"
    },
    {
      "path": "src/components/deck/HomeProjectList.tsx",
      "kind": "project folder download wires current browser artifact writes into export"
    },
    {
      "path": "docs/live-evidence/codex-image/lane-g-closure-recheck-20260621/issue-closure-evidence.json",
      "sha256": "cce49011bc94260509f1f4c4e0fb8753ecaff53e8a4313206cea8de1b718f13d",
      "kind": "blocked image/export/usage closure recheck"
    },
    {
      "path": "projects/df244_generate_export_smoke_20260622/live-evidence/df233-image-queue-job_generate_export_smoke_1.json",
      "sha256": "0c0b2dc64b57f8c86c87a06c367819bd8c839353e0571a4cd4e5bf99ce960df9",
      "kind": "real Codex one-slide product queue evidence smoke"
    },
    {
      "path": "docs/live-evidence/codex-image/df233-queue-controls-smoke-20260622/summary.json",
      "sha256": "078631d92f8276e6e47fd77b872e81faebae04966a4258dbcd3733b954a3a7b7",
      "kind": "product queue retry and restart-resume smoke summary"
    },
    {
      "path": "projects/df233_queue_retry_smoke_20260622/live-evidence/df233-image-queue-retry_product_run_20260622.json",
      "sha256": "b162c6c406778b43449bbfd84f6e30a9cc76896d853b57e40f8f314464856ffe",
      "kind": "ready product queue 5xx retry evidence"
    },
    {
      "path": "projects/df233_queue_resume_smoke_20260622/live-evidence/df233-image-queue-resume_product_run_20260622.json",
      "sha256": "4c9916e639dbf0b8c07ff62713ea31abec9d5a09a9376fd1ca0fa30a1ae5f4ab",
      "kind": "ready product queue restart-resume evidence"
    },
    {
      "path": "scripts/run-df233-queue-controls-product-evidence-smoke.ts",
      "kind": "reproducible product queue-control evidence smoke"
    }
  ],
  "missingEvidence": [
    "packaged Codex OAuth image run with genuine 429 or 5xx retry provenance",
    "in-flight user cancellation evidence from a real provider job",
    "restart-resume evidence proving completed slides are not regenerated",
    "stored versioned PNG artifact paths for every completed packaged queue slide",
    "product-generated DF-233 queue evidence JSON from a packaged run exported through project folder and copied into docs/live-evidence"
  ]
}
