{
  "ticketId": "DF-247",
  "issueNumber": 157,
  "status": "blocked",
  "validationKind": "blocked",
  "generatedAt": "2026-06-22T02:25:38Z",
  "packageArchiveSha256": "e6ed0e25791dd51a1c206247bd0faf5a1010aaee6c7b16e7256dfd25f74f47f6",
  "summary": "The final release gate remains blocked because upstream packaged evidence entries are blocked, DF-245 now has persisted release-trust blocker output rather than passed trust evidence, DF-246 only has current-package manual QA handoff evidence rather than a non-developer session, and the release decision is not approved; borrowed release decision payloads are also blocked before readiness.",
  "currentEvidence": [
    {
      "path": "docs/live-release-decision.md",
      "kind": "canonical blocked release decision"
    },
    {
      "path": "docs/live-evidence/release/packaged-live-evidence-index.json",
      "kind": "shared packaged evidence index"
    },
    {
      "path": "docs/live-evidence/release/df246-evidence.json",
      "sha256": "b15d0cc140cc2c01176c6bbae4d5ef3d7353b6159397974b50c034493e30543e",
      "kind": "DF-246 current-package manual QA handoff evidence, still blocked without non-developer session"
    },
    {
      "path": "docs/live-evidence/release/df245-package-recheck-20260622.json",
      "sha256": "7b9adb24eca8a6f27bedb2adbe1c5221d1ae9c1470a5e420589e391ddaf73a47",
      "kind": "current package and signing blocker recheck"
    },
    {
      "path": "docs/live-evidence/release/df245-evidence.json",
      "sha256": "111a3d346269e8bff75eb02afd1c9099ab2bf3e91a7d79f82162543809a81244",
      "kind": "blocked DF-245 packaging evidence with current release-trust blocker bundle reference"
    },
    {
      "path": "docs/live-evidence/release/df245-release-trust-codesign-notarytool-stapler-spctl-20260622.json",
      "sha256": "39abe3e0d644cde5797894509909f49eb8224a918ac70baaec807a0eb5361fa7",
      "kind": "persisted blocked release-trust command bundle for DF-245 final-gate blocker traceability"
    },
    {
      "path": "src/lib/packaged-live-evidence-index.ts",
      "kind": "packaged evidence index validator with ticket-token path binding"
    },
    {
      "path": "src/lib/live-release-decision-gate.ts",
      "kind": "release decision payload validator"
    },
    {
      "path": "src/lib/live-release-gate.test.ts",
      "kind": "borrowed release decision payload regression coverage"
    }
  ],
  "missingEvidence": [
    "all P0 tickets verified live",
    "ready DF-241 Golden Path evidence",
    "ready DF-242 benchmark evidence",
    "ready DF-243 interruption evidence",
    "ready DF-245 packaging trust and clean-machine evidence",
    "ready DF-246 non-developer manual QA evidence",
    "approved release decision in docs/live-release-decision.md"
  ]
}
