{
  "ticketId": "DF-246",
  "issueNumber": 156,
  "status": "blocked",
  "validationKind": "blocked",
  "generatedAt": "2026-06-21T20:56:40Z",
  "packageArchiveSha256": "aacadd4cd4546ce20b084b1fbf8018e9571a635983ad9aa30b07a123c705985e",
  "summary": "Manual QA validator and checklist exist, and temporary or observer session evidence paths are blocked before readiness, but no non-developer packaged-app manual QA session bundle has been recorded.",
  "currentEvidence": [
    {
      "path": "docs/live-manual-qa-checklist.md",
      "kind": "manual QA checklist"
    },
    {
      "path": "docs/live-release-decision.md",
      "kind": "release decision recording missing non-developer manual QA"
    },
    {
      "path": "src/lib/live-manual-qa-session-evidence.ts",
      "kind": "manual QA session evidence path validator"
    },
    {
      "path": "src/lib/live-manual-qa-session-evidence.test.ts",
      "kind": "temporary session evidence path regression coverage"
    }
  ],
  "missingEvidence": [
    "non-developer tester session evidence JSON",
    "setup under ten minutes with new project, login check, and prompt input",
    "research_pack, slide_generation, and export approval target checks",
    "real source opened and linked in final report",
    "regeneration and title edit actions",
    "PNG, project, and report export opens",
    "severity issue list with zero P0 and zero critical errors"
  ]
}
